pypolar/__init__.py
pypolar/ellipsometry.py
pypolar/fresnel.py
pypolar/gaertner.py
pypolar/jones.py
pypolar/mueller.py
pypolar/sym_fresnel.py
pypolar/sym_jones.py
pypolar/sym_mueller.py
pypolar/visualization.py
pypolar-1.0.2.dist-info/licenses/LICENSE.txt
pypolar-1.0.2.dist-info/METADATA
pypolar-1.0.2.dist-info/WHEEL
pypolar-1.0.2.dist-info/top_level.txt
pypolar-1.0.2.dist-info/RECORD
