Metadata-Version: 2.4
Name: pypolar
Version: 1.0.2
Summary: Routines for analysis of polarization
Author-email: Scott Prahl <scott.prahl@oit.edu>
License-Expression: MIT
Project-URL: Homepage, https://github.com/scottprahl/pypolar
Project-URL: Documentation, https://pypolar.readthedocs.io
Project-URL: Source, https://github.com/scottprahl/pypolar
Project-URL: Tracker, https://github.com/scottprahl/pypolar/issues
Project-URL: Changelog, https://github.com/scottprahl/pypolar/blob/main/docs/CHANGELOG.rst
Keywords: retarder,quarter wave,half wave,Jones calculus,birefringent,ellipsometry,Fresnel,Mueller calculus,Stokes vector
Classifier: Development Status :: 5 - Production/Stable
Classifier: Intended Audience :: Science/Research
Classifier: Topic :: Scientific/Engineering
Classifier: Programming Language :: Python
Classifier: Programming Language :: Python :: 3
Classifier: Programming Language :: Python :: 3.9
Classifier: Programming Language :: Python :: 3.10
Classifier: Programming Language :: Python :: 3.11
Classifier: Programming Language :: Python :: 3.12
Requires-Python: >=3.9
License-File: LICENSE.txt
Requires-Dist: numpy
Requires-Dist: matplotlib
Requires-Dist: scipy
Requires-Dist: sympy
Provides-Extra: docs
Requires-Dist: Sphinx==8.1.3; extra == "docs"
Requires-Dist: nbsphinx==0.9.7; extra == "docs"
Requires-Dist: sphinx_automodapi; extra == "docs"
Requires-Dist: sphinx_rtd_theme; extra == "docs"
Provides-Extra: dev
Requires-Dist: pyserial; extra == "dev"
Requires-Dist: ipywidgets; extra == "dev"
Requires-Dist: pytest; extra == "dev"
Requires-Dist: ruff; extra == "dev"
Requires-Dist: yamllint; extra == "dev"
Requires-Dist: rstcheck; extra == "dev"
Requires-Dist: pylint; extra == "dev"
Requires-Dist: pyroma; extra == "dev"
Requires-Dist: black[jupyter]; extra == "dev"
Requires-Dist: build; extra == "dev"
Requires-Dist: check-manifest; extra == "dev"
Requires-Dist: libarchive-c; extra == "dev"
Requires-Dist: pyyaml; extra == "dev"
Requires-Dist: setuptools; extra == "dev"
Requires-Dist: jupyterlab; extra == "dev"
Requires-Dist: nbconvert; extra == "dev"
Requires-Dist: nbformat; extra == "dev"
Provides-Extra: lite
Requires-Dist: jupyterlite-core==0.6.4; extra == "lite"
Requires-Dist: jupyterlite-pyodide-kernel==0.6.1; extra == "lite"
Dynamic: license-file
